{
  "project_info": {
    "project_number": "498454539131",
    "firebase_url": "https://beerprominiprojekt.firebaseio.com",
    "project_id": "beerprominiprojekt",
    "storage_bucket": "beerprominiprojekt.appspot.com"
  },
  "client": [
    {
      "client_info": {
        "mobilesdk_app_id": "1:498454539131:android:cf92c139ddcef4a8",
        "android_client_info": {
          "package_name": "ch.beerpro"
        }
      },
      "oauth_client": [
        {
          "client_id": "498454539131-idd49m70v9c2le87gicd1mj0pv2utovt.apps.googleusercontent.com",
          "client_type": 3
        }
      ],
      "api_key": [
        {
          "current_key": "AIzaSyCheY48JLc3T7j95aHtXpKQQ0ZKhmQaeNQ"
        }
      ],
      "services": {
        "analytics_service": {
          "status": 1
        },
        "appinvite_service": {
          "status": 1,
          "other_platform_oauth_client": []
        },
        "ads_service": {
          "status": 2
        }
      }
    }
  ],
  "configuration_version": "1"
}